gha_stats/__init__.py
gha_stats/cli.py
gha_stats/config.py
gha_stats/database.py
gha_stats-0.1.1.dist-info/entry_points.txt
gha_stats-0.1.1.dist-info/WHEEL
gha_stats-0.1.1.dist-info/METADATA
gha_stats-0.1.1.dist-info/RECORD
