Metadata-Version: 2.1
Name: gha-stats
Version: 0.1.1
Summary: 
Author: Paul Gessinger
Author-email: hello@paulgessinger.com
Requires-Python: >=3.8,<4.0
Classifier: Programming Language :: Python :: 3
Classifier: Programming Language :: Python :: 3.10
Classifier: Programming Language :: Python :: 3.8
Classifier: Programming Language :: Python :: 3.9
Requires-Dist: aiohttp (>=3.7.4,<4.0.0)
Requires-Dist: cachetools (>=5.1.0,<6.0.0)
Requires-Dist: gidgethub (>=5.0.1,<6.0.0)
Requires-Dist: matplotlib (>=3.5.2,<4.0.0)
Requires-Dist: more-itertools (>=8.13.0,<9.0.0)
Requires-Dist: pandas (>=1.4.2,<2.0.0)
Requires-Dist: peewee (>=3.14.10,<4.0.0)
Requires-Dist: pysqlite3 (>=0.4.7,<0.5.0); sys_platform == "darwin"
Requires-Dist: pysqlite3-binary (>=0.4.7,<0.5.0); sys_platform == "linux"
Requires-Dist: python-dateutil (>=2.8.2,<3.0.0)
Requires-Dist: python-dotenv (>=0.17.1,<0.18.0)
Requires-Dist: rich (>=12.4.2,<13.0.0)
Requires-Dist: typer (>=0.4.1,<0.5.0)
